tfweb/__init__.py
tfweb/batcher.py
tfweb/grpc_handler.py
tfweb/json_handler.py
tfweb/model.py
tfweb/service_grpc.py
tfweb/service_pb2.py
tfweb/tfweb.py
tfweb-0.4.4.data/scripts/tfweb
tfweb-0.4.4.dist-info/METADATA
tfweb-0.4.4.dist-info/WHEEL
tfweb-0.4.4.dist-info/top_level.txt
tfweb-0.4.4.dist-info/RECORD
