Metadata-Version: 2.1
Name: tfweb
Version: 0.4.4
Summary: Server for exposing tensorflow models though HTTP JSON API
Home-page: https://github.com/olavhn/tfweb
Author: Olav Nymoen
Author-email: olav@olavnymoen.com
License: MIT
Keywords: serving,tensorflow,asyncio,aiohttp,grpc
Platform: UNKNOWN
Classifier: Development Status :: 3 - Alpha
Classifier: Intended Audience :: Developers
Classifier: Topic :: Software Development :: Build Tools
Classifier: License :: OSI Approved :: MIT License
Classifier: Programming Language :: Python :: 3.6
Requires-Python: >=3.5
Requires-Dist: aiohttp (>=2)
Requires-Dist: aiohttp-cors (>=0.7)
Requires-Dist: grpclib (>=0.1)
